{
  "ActivationMapId": 3210,
  "Activations": [
    {
      "AreaId": 3210,
      "Location": {
        "X": 70,
        "Y": 51
      },
      "PortalKey": 0
    },
    {
      "AreaId": 3210,
      "Location": {
        "X": 70,
        "Y": 52
      },
      "PortalKey": 0
    }
  ],
  "LevelRequired": 1,
  "To": {
    "AreaId": 3211,
    "Location": {
      "X": 23,
      "Y": 12
    },
    "PortalKey": 0
  },
  "WarpRadius": 0,
  "WarpType": 0,
  "WorldResetWarpId": 0,
  "WorldTransionWarpId": 0,
  "Description": null,
  "Group": null,
  "Name": "Warp from 3210 to 3211"
}