{
  "ActivationMapId": 10179,
  "Activations": [
    {
      "AreaId": 10179,
      "Location": {
        "X": 30,
        "Y": 16
      },
      "PortalKey": 0
    },
    {
      "AreaId": 10179,
      "Location": {
        "X": 30,
        "Y": 15
      },
      "PortalKey": 0
    }
  ],
  "LevelRequired": 1,
  "To": {
    "AreaId": 10169,
    "Location": {
      "X": 3,
      "Y": 22
    },
    "PortalKey": 0
  },
  "WarpRadius": 0,
  "WarpType": 0,
  "WorldResetWarpId": 0,
  "WorldTransionWarpId": 0,
  "Description": null,
  "Group": null,
  "Name": "Warp from 10179 to 10169"
}