{
  "ActivationMapId": 10217,
  "Activations": [
    {
      "AreaId": 10217,
      "Location": {
        "X": 1,
        "Y": 23
      },
      "PortalKey": 0
    },
    {
      "AreaId": 10217,
      "Location": {
        "X": 1,
        "Y": 22
      },
      "PortalKey": 0
    }
  ],
  "LevelRequired": 1,
  "To": {
    "AreaId": 10225,
    "Location": {
      "X": 28,
      "Y": 8
    },
    "PortalKey": 0
  },
  "WarpRadius": 0,
  "WarpType": 0,
  "WorldResetWarpId": 0,
  "WorldTransionWarpId": 0,
  "Description": null,
  "Group": null,
  "Name": "Warp from 10217 to 10225"
}