{
  "ActivationMapId": 8099,
  "Activations": [
    {
      "AreaId": 8099,
      "Location": {
        "X": 10,
        "Y": 25
      },
      "PortalKey": 0
    },
    {
      "AreaId": 8099,
      "Location": {
        "X": 11,
        "Y": 25
      },
      "PortalKey": 0
    },
    {
      "AreaId": 8099,
      "Location": {
        "X": 12,
        "Y": 25
      },
      "PortalKey": 0
    }
  ],
  "LevelRequired": 1,
  "To": {
    "AreaId": 3210,
    "Location": {
      "X": 70,
      "Y": 31
    },
    "PortalKey": 0
  },
  "WarpRadius": 0,
  "WarpType": 0,
  "WorldResetWarpId": 0,
  "WorldTransionWarpId": 0,
  "Description": null,
  "Group": null,
  "Name": "Warp from 8099 to 3210"
}